qilbeedb/__init__.py
qilbeedb/auth.py
qilbeedb/client.py
qilbeedb/exceptions.py
qilbeedb/graph.py
qilbeedb/memory.py
qilbeedb/query.py
qilbeedb-0.2.1.dist-info/licenses/LICENSE
qilbeedb-0.2.1.dist-info/METADATA
qilbeedb-0.2.1.dist-info/WHEEL
qilbeedb-0.2.1.dist-info/top_level.txt
qilbeedb-0.2.1.dist-info/RECORD
