Metadata-Version: 2.4
Name: qilbeedb
Version: 0.2.1
Summary: Python SDK for QilbeeDB - Enterprise Graph Database with Agent Memory
Home-page: https://github.com/aicubetechnology/qilbeeDB
Author: AICUBE TECHNOLOGY LLC
Author-email: QilbeeDB Team <contact@aicube.ca>
Project-URL: Homepage, https://github.com/aicubetechnology/qilbeeDB
Project-URL: Documentation, https://docs.qilbeedb.io
Project-URL: Repository, https://github.com/aicubetechnology/qilbeeDB
Project-URL: Bug Tracker, https://github.com/aicubetechnology/qilbeeDB/issues
Keywords: graph,database,nosql,agent,memory,ai,temporal
Classifier: Development Status :: 3 - Alpha
Classifier: Intended Audience :: Developers
Classifier: Topic :: Database
Classifier: Topic :: Software Development :: Libraries :: Python Modules
Classifier: License :: Other/Proprietary License
Classifier: Programming Language :: Python :: 3
Classifier: Programming Language :: Python :: 3.8
Classifier: Programming Language :: Python :: 3.9
Classifier: Programming Language :: Python :: 3.10
Classifier: Programming Language :: Python :: 3.11
Classifier: Programming Language :: Python :: 3.12
Requires-Python: >=3.8
License-File: LICENSE
Requires-Dist: requests>=2.28.0
Provides-Extra: dev
Requires-Dist: pytest>=7.0.0; extra == "dev"
Requires-Dist: pytest-cov>=4.0.0; extra == "dev"
Requires-Dist: black>=23.0.0; extra == "dev"
Requires-Dist: flake8>=6.0.0; extra == "dev"
Requires-Dist: mypy>=1.0.0; extra == "dev"
Dynamic: author
Dynamic: home-page
Dynamic: license-file
Dynamic: requires-python
